[{"page":1,"pages":1,"per_page":200,"total":132,"sourceid":"2","lastupdated":"2026-04-08"},[{"indicator":{"id":"NV.IND.TOTL.KD.ZG","value":"Industry (including construction), value added (annual % growth)"},"country":{"id":"GH","value":"Ghana"},"countryiso3code":"GHA","date":"2025","value":null,"unit":"","obs_status":"","decimal":1},{"indicator":{"id":"NV.IND.TOTL.KD.ZG","value":"Industry (including construction), value added (annual % growth)"},"country":{"id":"GH","value":"Ghana"},"countryiso3code":"GHA","date":"2024","value":7.47636820539772,"unit":"","obs_status":"","decimal":1},{"indicator":{"id":"NV.IND.TOTL.KD.ZG","value":"Industry (including construction), value added (annual % growth)"},"country":{"id":"GH","value":"Ghana"},"countryiso3code":"GHA","date":"2023","value":-1.74556258124035,"unit":"","obs_status":"","decimal":1},{"indicator":{"id":"NV.IND.TOTL.KD.ZG","value":"Industry (including construction), value added (annual % growth)"},"country":{"id":"GH","value":"Ghana"},"countryiso3code":"GHA","date":"2022","value":0.593509861330972,"unit":"","obs_status":"","decimal":1},{"indicator":{"id":"NV.IND.TOTL.KD.ZG","value":"Industry (including construction), value added (annual % growth)"},"country":{"id":"GH","value":"Ghana"},"countryiso3code":"GHA","date":"2021","value":-0.478522570675352,"unit":"","obs_status":"","decimal":1},{"indicator":{"id":"NV.IND.TOTL.KD.ZG","value":"Industry (including construction), value added (annual % growth)"},"country":{"id":"GH","value":"Ghana"},"countryiso3code":"GHA","date":"2020","value":-2.49614161540688,"unit":"","obs_status":"","decimal":1},{"indicator":{"id":"NV.IND.TOTL.KD.ZG","value":"Industry (including construction), value added (annual % growth)"},"country":{"id":"GH","value":"Ghana"},"countryiso3code":"GHA","date":"2019","value":6.36581198422543,"unit":"","obs_status":"","decimal":1},{"indicator":{"id":"NV.IND.TOTL.KD.ZG","value":"Industry (including construction), value added (annual % growth)"},"country":{"id":"GH","value":"Ghana"},"countryiso3code":"GHA","date":"2018","value":10.5029940796845,"unit":"","obs_status":"","decimal":1},{"indicator":{"id":"NV.IND.TOTL.KD.ZG","value":"Industry (including construction), value added (annual % growth)"},"country":{"id":"GH","value":"Ghana"},"countryiso3code":"GHA","date":"2017","value":15.6144203810797,"unit":"","obs_status":"","decimal":1},{"indicator":{"id":"NV.IND.TOTL.KD.ZG","value":"Industry (including construction), value added (annual % growth)"},"country":{"id":"GH","value":"Ghana"},"countryiso3code":"GHA","date":"2016","value":4.32268740848467,"unit":"","obs_status":"","decimal":1},{"indicator":{"id":"NV.IND.TOTL.KD.ZG","value":"Industry (including construction), value added (annual % growth)"},"country":{"id":"GH","value":"Ghana"},"countryiso3code":"GHA","date":"2015","value":1.15130193146381,"unit":"","obs_status":"","decimal":1},{"indicator":{"id":"NV.IND.TOTL.KD.ZG","value":"Industry (including construction), value added (annual % growth)"},"country":{"id":"GH","value":"Ghana"},"countryiso3code":"GHA","date":"2014","value":1.13094972038969,"unit":"","obs_status":"","decimal":1},{"indicator":{"id":"NV.IND.TOTL.KD.ZG","value":"Industry (including construction), value added (annual % growth)"},"country":{"id":"GH","value":"Ghana"},"countryiso3code":"GHA","date":"2013","value":4.98557141253939,"unit":"","obs_status":"","decimal":1},{"indicator":{"id":"NV.IND.TOTL.KD.ZG","value":"Industry (including construction), value added (annual % growth)"},"country":{"id":"GH","value":"Ghana"},"countryiso3code":"GHA","date":"2012","value":11.043570404346,"unit":"","obs_status":"","decimal":1},{"indicator":{"id":"NV.IND.TOTL.KD.ZG","value":"Industry (including construction), value added (annual % growth)"},"country":{"id":"GH","value":"Ghana"},"countryiso3code":"GHA","date":"2011","value":41.6397703726642,"unit":"","obs_status":"","decimal":1},{"indicator":{"id":"NV.IND.TOTL.KD.ZG","value":"Industry (including construction), value added (annual % growth)"},"country":{"id":"GH","value":"Ghana"},"countryiso3code":"GHA","date":"2010","value":6.94739665261793,"unit":"","obs_status":"","decimal":1},{"indicator":{"id":"NV.IND.TOTL.KD.ZG","value":"Industry (including construction), value added (annual % growth)"},"country":{"id":"GH","value":"Ghana"},"countryiso3code":"GHA","date":"2009","value":4.4868282801532,"unit":"","obs_status":"","decimal":1},{"indicator":{"id":"NV.IND.TOTL.KD.ZG","value":"Industry (including construction), value added (annual % growth)"},"country":{"id":"GH","value":"Ghana"},"countryiso3code":"GHA","date":"2008","value":15.0700626638991,"unit":"","obs_status":"","decimal":1},{"indicator":{"id":"NV.IND.TOTL.KD.ZG","value":"Industry (including construction), value added (annual % growth)"},"country":{"id":"GH","value":"Ghana"},"countryiso3code":"GHA","date":"2007","value":6.08452481045954,"unit":"","obs_status":"","decimal":1},{"indicator":{"id":"NV.IND.TOTL.KD.ZG","value":"Industry (including construction), value added (annual % growth)"},"country":{"id":"GH","value":"Ghana"},"countryiso3code":"GHA","date":"2006","value":null,"unit":"","obs_status":"","decimal":1},{"indicator":{"id":"NV.IND.TOTL.KD.ZG","value":"Industry (including construction), value added (annual % growth)"},"country":{"id":"GH","value":"Ghana"},"countryiso3code":"GHA","date":"2005","value":null,"unit":"","obs_status":"","decimal":1},{"indicator":{"id":"NV.IND.TOTL.KD.ZG","value":"Industry (including construction), value added (annual % growth)"},"country":{"id":"GH","value":"Ghana"},"countryiso3code":"GHA","date":"2004","value":null,"unit":"","obs_status":"","decimal":1},{"indicator":{"id":"NV.IND.TOTL.KD.ZG","value":"Industry (including construction), value added (annual % growth)"},"country":{"id":"GH","value":"Ghana"},"countryiso3code":"GHA","date":"2003","value":null,"unit":"","obs_status":"","decimal":1},{"indicator":{"id":"NV.IND.TOTL.KD.ZG","value":"Industry (including construction), value added (annual % growth)"},"country":{"id":"GH","value":"Ghana"},"countryiso3code":"GHA","date":"2002","value":null,"unit":"","obs_status":"","decimal":1},{"indicator":{"id":"NV.IND.TOTL.KD.ZG","value":"Industry (including construction), value added (annual % growth)"},"country":{"id":"GH","value":"Ghana"},"countryiso3code":"GHA","date":"2001","value":null,"unit":"","obs_status":"","decimal":1},{"indicator":{"id":"NV.IND.TOTL.KD.ZG","value":"Industry (including construction), value added (annual % growth)"},"country":{"id":"GH","value":"Ghana"},"countryiso3code":"GHA","date":"2000","value":null,"unit":"","obs_status":"","decimal":1},{"indicator":{"id":"NV.IND.TOTL.KD.ZG","value":"Industry (including construction), value added (annual % growth)"},"country":{"id":"GH","value":"Ghana"},"countryiso3code":"GHA","date":"1999","value":null,"unit":"","obs_status":"","decimal":1},{"indicator":{"id":"NV.IND.TOTL.KD.ZG","value":"Industry (including construction), value added (annual % growth)"},"country":{"id":"GH","value":"Ghana"},"countryiso3code":"GHA","date":"1998","value":null,"unit":"","obs_status":"","decimal":1},{"indicator":{"id":"NV.IND.TOTL.KD.ZG","value":"Industry (including construction), value added (annual % growth)"},"country":{"id":"GH","value":"Ghana"},"countryiso3code":"GHA","date":"1997","value":null,"unit":"","obs_status":"","decimal":1},{"indicator":{"id":"NV.IND.TOTL.KD.ZG","value":"Industry (including construction), value added (annual % growth)"},"country":{"id":"GH","value":"Ghana"},"countryiso3code":"GHA","date":"1996","value":null,"unit":"","obs_status":"","decimal":1},{"indicator":{"id":"NV.IND.TOTL.KD.ZG","value":"Industry (including construction), value added (annual % growth)"},"country":{"id":"GH","value":"Ghana"},"countryiso3code":"GHA","date":"1995","value":null,"unit":"","obs_status":"","decimal":1},{"indicator":{"id":"NV.IND.TOTL.KD.ZG","value":"Industry (including construction), value added (annual % growth)"},"country":{"id":"GH","value":"Ghana"},"countryiso3code":"GHA","date":"1994","value":null,"unit":"","obs_status":"","decimal":1},{"indicator":{"id":"NV.IND.TOTL.KD.ZG","value":"Industry (including construction), value added (annual % growth)"},"country":{"id":"GH","value":"Ghana"},"countryiso3code":"GHA","date":"1993","value":null,"unit":"","obs_status":"","decimal":1},{"indicator":{"id":"NV.IND.TOTL.KD.ZG","value":"Industry (including construction), value added (annual % growth)"},"country":{"id":"GH","value":"Ghana"},"countryiso3code":"GHA","date":"1992","value":null,"unit":"","obs_status":"","decimal":1},{"indicator":{"id":"NV.IND.TOTL.KD.ZG","value":"Industry (including construction), value added (annual % growth)"},"country":{"id":"GH","value":"Ghana"},"countryiso3code":"GHA","date":"1991","value":null,"unit":"","obs_status":"","decimal":1},{"indicator":{"id":"NV.IND.TOTL.KD.ZG","value":"Industry (including construction), value added (annual % growth)"},"country":{"id":"GH","value":"Ghana"},"countryiso3code":"GHA","date":"1990","value":null,"unit":"","obs_status":"","decimal":1},{"indicator":{"id":"NV.IND.TOTL.KD.ZG","value":"Industry (including construction), value added (annual % growth)"},"country":{"id":"GH","value":"Ghana"},"countryiso3code":"GHA","date":"1989","value":null,"unit":"","obs_status":"","decimal":1},{"indicator":{"id":"NV.IND.TOTL.KD.ZG","value":"Industry (including construction), value added (annual % growth)"},"country":{"id":"GH","value":"Ghana"},"countryiso3code":"GHA","date":"1988","value":null,"unit":"","obs_status":"","decimal":1},{"indicator":{"id":"NV.IND.TOTL.KD.ZG","value":"Industry (including construction), value added (annual % growth)"},"country":{"id":"GH","value":"Ghana"},"countryiso3code":"GHA","date":"1987","value":null,"unit":"","obs_status":"","decimal":1},{"indicator":{"id":"NV.IND.TOTL.KD.ZG","value":"Industry (including construction), value added (annual % growth)"},"country":{"id":"GH","value":"Ghana"},"countryiso3code":"GHA","date":"1986","value":null,"unit":"","obs_status":"","decimal":1},{"indicator":{"id":"NV.IND.TOTL.KD.ZG","value":"Industry (including construction), value added (annual % growth)"},"country":{"id":"GH","value":"Ghana"},"countryiso3code":"GHA","date":"1985","value":null,"unit":"","obs_status":"","decimal":1},{"indicator":{"id":"NV.IND.TOTL.KD.ZG","value":"Industry (including construction), value added (annual % growth)"},"country":{"id":"GH","value":"Ghana"},"countryiso3code":"GHA","date":"1984","value":null,"unit":"","obs_status":"","decimal":1},{"indicator":{"id":"NV.IND.TOTL.KD.ZG","value":"Industry (including construction), value added (annual % growth)"},"country":{"id":"GH","value":"Ghana"},"countryiso3code":"GHA","date":"1983","value":null,"unit":"","obs_status":"","decimal":1},{"indicator":{"id":"NV.IND.TOTL.KD.ZG","value":"Industry (including construction), value added (annual % growth)"},"country":{"id":"GH","value":"Ghana"},"countryiso3code":"GHA","date":"1982","value":null,"unit":"","obs_status":"","decimal":1},{"indicator":{"id":"NV.IND.TOTL.KD.ZG","value":"Industry (including construction), value added (annual % growth)"},"country":{"id":"GH","value":"Ghana"},"countryiso3code":"GHA","date":"1981","value":null,"unit":"","obs_status":"","decimal":1},{"indicator":{"id":"NV.IND.TOTL.KD.ZG","value":"Industry (including construction), value added (annual % growth)"},"country":{"id":"GH","value":"Ghana"},"countryiso3code":"GHA","date":"1980","value":null,"unit":"","obs_status":"","decimal":1},{"indicator":{"id":"NV.IND.TOTL.KD.ZG","value":"Industry (including construction), value added (annual % growth)"},"country":{"id":"GH","value":"Ghana"},"countryiso3code":"GHA","date":"1979","value":null,"unit":"","obs_status":"","decimal":1},{"indicator":{"id":"NV.IND.TOTL.KD.ZG","value":"Industry (including construction), value added (annual % growth)"},"country":{"id":"GH","value":"Ghana"},"countryiso3code":"GHA","date":"1978","value":null,"unit":"","obs_status":"","decimal":1},{"indicator":{"id":"NV.IND.TOTL.KD.ZG","value":"Industry (including construction), value added (annual % growth)"},"country":{"id":"GH","value":"Ghana"},"countryiso3code":"GHA","date":"1977","value":null,"unit":"","obs_status":"","decimal":1},{"indicator":{"id":"NV.IND.TOTL.KD.ZG","value":"Industry (including construction), value added (annual % growth)"},"country":{"id":"GH","value":"Ghana"},"countryiso3code":"GHA","date":"1976","value":null,"unit":"","obs_status":"","decimal":1},{"indicator":{"id":"NV.IND.TOTL.KD.ZG","value":"Industry (including construction), value added (annual % growth)"},"country":{"id":"GH","value":"Ghana"},"countryiso3code":"GHA","date":"1975","value":null,"unit":"","obs_status":"","decimal":1},{"indicator":{"id":"NV.IND.TOTL.KD.ZG","value":"Industry (including construction), value added (annual % growth)"},"country":{"id":"GH","value":"Ghana"},"countryiso3code":"GHA","date":"1974","value":null,"unit":"","obs_status":"","decimal":1},{"indicator":{"id":"NV.IND.TOTL.KD.ZG","value":"Industry (including construction), value added (annual % growth)"},"country":{"id":"GH","value":"Ghana"},"countryiso3code":"GHA","date":"1973","value":null,"unit":"","obs_status":"","decimal":1},{"indicator":{"id":"NV.IND.TOTL.KD.ZG","value":"Industry (including construction), value added (annual % growth)"},"country":{"id":"GH","value":"Ghana"},"countryiso3code":"GHA","date":"1972","value":null,"unit":"","obs_status":"","decimal":1},{"indicator":{"id":"NV.IND.TOTL.KD.ZG","value":"Industry (including construction), value added (annual % growth)"},"country":{"id":"GH","value":"Ghana"},"countryiso3code":"GHA","date":"1971","value":null,"unit":"","obs_status":"","decimal":1},{"indicator":{"id":"NV.IND.TOTL.KD.ZG","value":"Industry (including construction), value added (annual % growth)"},"country":{"id":"GH","value":"Ghana"},"countryiso3code":"GHA","date":"1970","value":null,"unit":"","obs_status":"","decimal":1},{"indicator":{"id":"NV.IND.TOTL.KD.ZG","value":"Industry (including construction), value added (annual % growth)"},"country":{"id":"GH","value":"Ghana"},"countryiso3code":"GHA","date":"1969","value":null,"unit":"","obs_status":"","decimal":1},{"indicator":{"id":"NV.IND.TOTL.KD.ZG","value":"Industry (including construction), value added (annual % growth)"},"country":{"id":"GH","value":"Ghana"},"countryiso3code":"GHA","date":"1968","value":null,"unit":"","obs_status":"","decimal":1},{"indicator":{"id":"NV.IND.TOTL.KD.ZG","value":"Industry (including construction), value added (annual % growth)"},"country":{"id":"GH","value":"Ghana"},"countryiso3code":"GHA","date":"1967","value":null,"unit":"","obs_status":"","decimal":1},{"indicator":{"id":"NV.IND.TOTL.KD.ZG","value":"Industry (including construction), value added (annual % growth)"},"country":{"id":"GH","value":"Ghana"},"countryiso3code":"GHA","date":"1966","value":null,"unit":"","obs_status":"","decimal":1},{"indicator":{"id":"NV.IND.TOTL.KD.ZG","value":"Industry (including construction), value added (annual % growth)"},"country":{"id":"GH","value":"Ghana"},"countryiso3code":"GHA","date":"1965","value":null,"unit":"","obs_status":"","decimal":1},{"indicator":{"id":"NV.IND.TOTL.KD.ZG","value":"Industry (including construction), value added (annual % growth)"},"country":{"id":"GH","value":"Ghana"},"countryiso3code":"GHA","date":"1964","value":null,"unit":"","obs_status":"","decimal":1},{"indicator":{"id":"NV.IND.TOTL.KD.ZG","value":"Industry (including construction), value added (annual % growth)"},"country":{"id":"GH","value":"Ghana"},"countryiso3code":"GHA","date":"1963","value":null,"unit":"","obs_status":"","decimal":1},{"indicator":{"id":"NV.IND.TOTL.KD.ZG","value":"Industry (including construction), value added (annual % growth)"},"country":{"id":"GH","value":"Ghana"},"countryiso3code":"GHA","date":"1962","value":null,"unit":"","obs_status":"","decimal":1},{"indicator":{"id":"NV.IND.TOTL.KD.ZG","value":"Industry (including construction), value added (annual % growth)"},"country":{"id":"GH","value":"Ghana"},"countryiso3code":"GHA","date":"1961","value":null,"unit":"","obs_status":"","decimal":1},{"indicator":{"id":"NV.IND.TOTL.KD.ZG","value":"Industry (including construction), value added (annual % growth)"},"country":{"id":"GH","value":"Ghana"},"countryiso3code":"GHA","date":"1960","value":null,"unit":"","obs_status":"","decimal":1},{"indicator":{"id":"NV.IND.TOTL.KD.ZG","value":"Industry (including construction), value added (annual % growth)"},"country":{"id":"IN","value":"India"},"countryiso3code":"IND","date":"2025","value":null,"unit":"","obs_status":"","decimal":1},{"indicator":{"id":"NV.IND.TOTL.KD.ZG","value":"Industry (including construction), value added (annual % growth)"},"country":{"id":"IN","value":"India"},"countryiso3code":"IND","date":"2024","value":5.89982476604236,"unit":"","obs_status":"","decimal":1},{"indicator":{"id":"NV.IND.TOTL.KD.ZG","value":"Industry (including construction), value added (annual % growth)"},"country":{"id":"IN","value":"India"},"countryiso3code":"IND","date":"2023","value":10.8187162604096,"unit":"","obs_status":"","decimal":1},{"indicator":{"id":"NV.IND.TOTL.KD.ZG","value":"Industry (including construction), value added (annual % growth)"},"country":{"id":"IN","value":"India"},"countryiso3code":"IND","date":"2022","value":2.48450009467336,"unit":"","obs_status":"","decimal":1},{"indicator":{"id":"NV.IND.TOTL.KD.ZG","value":"Industry (including construction), value added (annual % growth)"},"country":{"id":"IN","value":"India"},"countryiso3code":"IND","date":"2021","value":12.2441238733607,"unit":"","obs_status":"","decimal":1},{"indicator":{"id":"NV.IND.TOTL.KD.ZG","value":"Industry (including construction), value added (annual % growth)"},"country":{"id":"IN","value":"India"},"countryiso3code":"IND","date":"2020","value":-0.439885659435575,"unit":"","obs_status":"","decimal":1},{"indicator":{"id":"NV.IND.TOTL.KD.ZG","value":"Industry (including construction), value added (annual % growth)"},"country":{"id":"IN","value":"India"},"countryiso3code":"IND","date":"2019","value":-1.40003274191449,"unit":"","obs_status":"","decimal":1},{"indicator":{"id":"NV.IND.TOTL.KD.ZG","value":"Industry (including construction), value added (annual % growth)"},"country":{"id":"IN","value":"India"},"countryiso3code":"IND","date":"2018","value":5.31641149108326,"unit":"","obs_status":"","decimal":1},{"indicator":{"id":"NV.IND.TOTL.KD.ZG","value":"Industry (including construction), value added (annual % growth)"},"country":{"id":"IN","value":"India"},"countryiso3code":"IND","date":"2017","value":5.86054231753634,"unit":"","obs_status":"","decimal":1},{"indicator":{"id":"NV.IND.TOTL.KD.ZG","value":"Industry (including construction), value added (annual % growth)"},"country":{"id":"IN","value":"India"},"countryiso3code":"IND","date":"2016","value":7.72008397972867,"unit":"","obs_status":"","decimal":1},{"indicator":{"id":"NV.IND.TOTL.KD.ZG","value":"Industry (including construction), value added (annual % growth)"},"country":{"id":"IN","value":"India"},"countryiso3code":"IND","date":"2015","value":9.57734616558422,"unit":"","obs_status":"","decimal":1},{"indicator":{"id":"NV.IND.TOTL.KD.ZG","value":"Industry (including construction), value added (annual % growth)"},"country":{"id":"IN","value":"India"},"countryiso3code":"IND","date":"2014","value":7.0006334861971,"unit":"","obs_status":"","decimal":1},{"indicator":{"id":"NV.IND.TOTL.KD.ZG","value":"Industry (including construction), value added (annual % growth)"},"country":{"id":"IN","value":"India"},"countryiso3code":"IND","date":"2013","value":3.78589190610872,"unit":"","obs_status":"","decimal":1},{"indicator":{"id":"NV.IND.TOTL.KD.ZG","value":"Industry (including construction), value added (annual % growth)"},"country":{"id":"IN","value":"India"},"countryiso3code":"IND","date":"2012","value":3.26918054242262,"unit":"","obs_status":"","decimal":1},{"indicator":{"id":"NV.IND.TOTL.KD.ZG","value":"Industry (including construction), value added (annual % growth)"},"country":{"id":"IN","value":"India"},"countryiso3code":"IND","date":"2011","value":3.62645039298488,"unit":"","obs_status":"","decimal":1},{"indicator":{"id":"NV.IND.TOTL.KD.ZG","value":"Industry (including construction), value added (annual % growth)"},"country":{"id":"IN","value":"India"},"countryiso3code":"IND","date":"2010","value":7.89698022806063,"unit":"","obs_status":"","decimal":1},{"indicator":{"id":"NV.IND.TOTL.KD.ZG","value":"Industry (including construction), value added (annual % growth)"},"country":{"id":"IN","value":"India"},"countryiso3code":"IND","date":"2009","value":8.84457510119059,"unit":"","obs_status":"","decimal":1},{"indicator":{"id":"NV.IND.TOTL.KD.ZG","value":"Industry (including construction), value added (annual % growth)"},"country":{"id":"IN","value":"India"},"countryiso3code":"IND","date":"2008","value":3.99922669031739,"unit":"","obs_status":"","decimal":1},{"indicator":{"id":"NV.IND.TOTL.KD.ZG","value":"Industry (including construction), value added (annual % growth)"},"country":{"id":"IN","value":"India"},"countryiso3code":"IND","date":"2007","value":8.02387049242617,"unit":"","obs_status":"","decimal":1},{"indicator":{"id":"NV.IND.TOTL.KD.ZG","value":"Industry (including construction), value added (annual % growth)"},"country":{"id":"IN","value":"India"},"countryiso3code":"IND","date":"2006","value":13.2408335882642,"unit":"","obs_status":"","decimal":1},{"indicator":{"id":"NV.IND.TOTL.KD.ZG","value":"Industry (including construction), value added (annual % growth)"},"country":{"id":"IN","value":"India"},"countryiso3code":"IND","date":"2005","value":9.57328712895685,"unit":"","obs_status":"","decimal":1},{"indicator":{"id":"NV.IND.TOTL.KD.ZG","value":"Industry (including construction), value added (annual % growth)"},"country":{"id":"IN","value":"India"},"countryiso3code":"IND","date":"2004","value":9.74627719888792,"unit":"","obs_status":"","decimal":1},{"indicator":{"id":"NV.IND.TOTL.KD.ZG","value":"Industry (including construction), value added (annual % growth)"},"country":{"id":"IN","value":"India"},"countryiso3code":"IND","date":"2003","value":7.07671851711716,"unit":"","obs_status":"","decimal":1},{"indicator":{"id":"NV.IND.TOTL.KD.ZG","value":"Industry (including construction), value added (annual % growth)"},"country":{"id":"IN","value":"India"},"countryiso3code":"IND","date":"2002","value":7.27505328779499,"unit":"","obs_status":"","decimal":1},{"indicator":{"id":"NV.IND.TOTL.KD.ZG","value":"Industry (including construction), value added (annual % growth)"},"country":{"id":"IN","value":"India"},"countryiso3code":"IND","date":"2001","value":2.57105967045399,"unit":"","obs_status":"","decimal":1},{"indicator":{"id":"NV.IND.TOTL.KD.ZG","value":"Industry (including construction), value added (annual % growth)"},"country":{"id":"IN","value":"India"},"countryiso3code":"IND","date":"2000","value":5.79734793675509,"unit":"","obs_status":"","decimal":1},{"indicator":{"id":"NV.IND.TOTL.KD.ZG","value":"Industry (including construction), value added (annual % growth)"},"country":{"id":"IN","value":"India"},"countryiso3code":"IND","date":"1999","value":5.8704903913583,"unit":"","obs_status":"","decimal":1},{"indicator":{"id":"NV.IND.TOTL.KD.ZG","value":"Industry (including construction), value added (annual % growth)"},"country":{"id":"IN","value":"India"},"countryiso3code":"IND","date":"1998","value":4.09409593537609,"unit":"","obs_status":"","decimal":1},{"indicator":{"id":"NV.IND.TOTL.KD.ZG","value":"Industry (including construction), value added (annual % growth)"},"country":{"id":"IN","value":"India"},"countryiso3code":"IND","date":"1997","value":4.39763171144811,"unit":"","obs_status":"","decimal":1},{"indicator":{"id":"NV.IND.TOTL.KD.ZG","value":"Industry (including construction), value added (annual % growth)"},"country":{"id":"IN","value":"India"},"countryiso3code":"IND","date":"1996","value":6.01009906896006,"unit":"","obs_status":"","decimal":1},{"indicator":{"id":"NV.IND.TOTL.KD.ZG","value":"Industry (including construction), value added (annual % growth)"},"country":{"id":"IN","value":"India"},"countryiso3code":"IND","date":"1995","value":10.8934388028237,"unit":"","obs_status":"","decimal":1},{"indicator":{"id":"NV.IND.TOTL.KD.ZG","value":"Industry (including construction), value added (annual % growth)"},"country":{"id":"IN","value":"India"},"countryiso3code":"IND","date":"1994","value":9.14675385626866,"unit":"","obs_status":"","decimal":1},{"indicator":{"id":"NV.IND.TOTL.KD.ZG","value":"Industry (including construction), value added (annual % growth)"},"country":{"id":"IN","value":"India"},"countryiso3code":"IND","date":"1993","value":5.20404060002093,"unit":"","obs_status":"","decimal":1},{"indicator":{"id":"NV.IND.TOTL.KD.ZG","value":"Industry (including construction), value added (annual % growth)"},"country":{"id":"IN","value":"India"},"countryiso3code":"IND","date":"1992","value":3.07891778058651,"unit":"","obs_status":"","decimal":1},{"indicator":{"id":"NV.IND.TOTL.KD.ZG","value":"Industry (including construction), value added (annual % growth)"},"country":{"id":"IN","value":"India"},"countryiso3code":"IND","date":"1991","value":0.586682301025448,"unit":"","obs_status":"","decimal":1},{"indicator":{"id":"NV.IND.TOTL.KD.ZG","value":"Industry (including construction), value added (annual % growth)"},"country":{"id":"IN","value":"India"},"countryiso3code":"IND","date":"1990","value":7.55550357840571,"unit":"","obs_status":"","decimal":1},{"indicator":{"id":"NV.IND.TOTL.KD.ZG","value":"Industry (including construction), value added (annual % growth)"},"country":{"id":"IN","value":"India"},"countryiso3code":"IND","date":"1989","value":8.25460141383954,"unit":"","obs_status":"","decimal":1},{"indicator":{"id":"NV.IND.TOTL.KD.ZG","value":"Industry (including construction), value added (annual % growth)"},"country":{"id":"IN","value":"India"},"countryiso3code":"IND","date":"1988","value":9.51426202326834,"unit":"","obs_status":"","decimal":1},{"indicator":{"id":"NV.IND.TOTL.KD.ZG","value":"Industry (including construction), value added (annual % growth)"},"country":{"id":"IN","value":"India"},"countryiso3code":"IND","date":"1987","value":5.46897321146476,"unit":"","obs_status":"","decimal":1},{"indicator":{"id":"NV.IND.TOTL.KD.ZG","value":"Industry (including construction), value added (annual % growth)"},"country":{"id":"IN","value":"India"},"countryiso3code":"IND","date":"1986","value":6.12662138747942,"unit":"","obs_status":"","decimal":1},{"indicator":{"id":"NV.IND.TOTL.KD.ZG","value":"Industry (including construction), value added (annual % growth)"},"country":{"id":"IN","value":"India"},"countryiso3code":"IND","date":"1985","value":4.46544087922661,"unit":"","obs_status":"","decimal":1},{"indicator":{"id":"NV.IND.TOTL.KD.ZG","value":"Industry (including construction), value added (annual % growth)"},"country":{"id":"IN","value":"India"},"countryiso3code":"IND","date":"1984","value":3.92349131587191,"unit":"","obs_status":"","decimal":1},{"indicator":{"id":"NV.IND.TOTL.KD.ZG","value":"Industry (including construction), value added (annual % growth)"},"country":{"id":"IN","value":"India"},"countryiso3code":"IND","date":"1983","value":7.54880468478684,"unit":"","obs_status":"","decimal":1},{"indicator":{"id":"NV.IND.TOTL.KD.ZG","value":"Industry (including construction), value added (annual % growth)"},"country":{"id":"IN","value":"India"},"countryiso3code":"IND","date":"1982","value":1.95914517812557,"unit":"","obs_status":"","decimal":1},{"indicator":{"id":"NV.IND.TOTL.KD.ZG","value":"Industry (including construction), value added (annual % growth)"},"country":{"id":"IN","value":"India"},"countryiso3code":"IND","date":"1981","value":8.29463316158518,"unit":"","obs_status":"","decimal":1},{"indicator":{"id":"NV.IND.TOTL.KD.ZG","value":"Industry (including construction), value added (annual % growth)"},"country":{"id":"IN","value":"India"},"countryiso3code":"IND","date":"1980","value":5.65054827219225,"unit":"","obs_status":"","decimal":1},{"indicator":{"id":"NV.IND.TOTL.KD.ZG","value":"Industry (including construction), value added (annual % growth)"},"country":{"id":"IN","value":"India"},"countryiso3code":"IND","date":"1979","value":-2.95924101727101,"unit":"","obs_status":"","decimal":1},{"indicator":{"id":"NV.IND.TOTL.KD.ZG","value":"Industry (including construction), value added (annual % growth)"},"country":{"id":"IN","value":"India"},"countryiso3code":"IND","date":"1978","value":6.61887708295643,"unit":"","obs_status":"","decimal":1},{"indicator":{"id":"NV.IND.TOTL.KD.ZG","value":"Industry (including construction), value added (annual % growth)"},"country":{"id":"IN","value":"India"},"countryiso3code":"IND","date":"1977","value":6.82266577003492,"unit":"","obs_status":"","decimal":1},{"indicator":{"id":"NV.IND.TOTL.KD.ZG","value":"Industry (including construction), value added (annual % growth)"},"country":{"id":"IN","value":"India"},"countryiso3code":"IND","date":"1976","value":8.40816139616109,"unit":"","obs_status":"","decimal":1},{"indicator":{"id":"NV.IND.TOTL.KD.ZG","value":"Industry (including construction), value added (annual % growth)"},"country":{"id":"IN","value":"India"},"countryiso3code":"IND","date":"1975","value":7.41877908656565,"unit":"","obs_status":"","decimal":1},{"indicator":{"id":"NV.IND.TOTL.KD.ZG","value":"Industry (including construction), value added (annual % growth)"},"country":{"id":"IN","value":"India"},"countryiso3code":"IND","date":"1974","value":1.56494045116462,"unit":"","obs_status":"","decimal":1},{"indicator":{"id":"NV.IND.TOTL.KD.ZG","value":"Industry (including construction), value added (annual % growth)"},"country":{"id":"IN","value":"India"},"countryiso3code":"IND","date":"1973","value":0.592743156699768,"unit":"","obs_status":"","decimal":1},{"indicator":{"id":"NV.IND.TOTL.KD.ZG","value":"Industry (including construction), value added (annual % growth)"},"country":{"id":"IN","value":"India"},"countryiso3code":"IND","date":"1972","value":3.7423334877781,"unit":"","obs_status":"","decimal":1},{"indicator":{"id":"NV.IND.TOTL.KD.ZG","value":"Industry (including construction), value added (annual % growth)"},"country":{"id":"IN","value":"India"},"countryiso3code":"IND","date":"1971","value":2.50995125294872,"unit":"","obs_status":"","decimal":1},{"indicator":{"id":"NV.IND.TOTL.KD.ZG","value":"Industry (including construction), value added (annual % growth)"},"country":{"id":"IN","value":"India"},"countryiso3code":"IND","date":"1970","value":0.348007684950886,"unit":"","obs_status":"","decimal":1},{"indicator":{"id":"NV.IND.TOTL.KD.ZG","value":"Industry (including construction), value added (annual % growth)"},"country":{"id":"IN","value":"India"},"countryiso3code":"IND","date":"1969","value":7.29374060714711,"unit":"","obs_status":"","decimal":1},{"indicator":{"id":"NV.IND.TOTL.KD.ZG","value":"Industry (including construction), value added (annual % growth)"},"country":{"id":"IN","value":"India"},"countryiso3code":"IND","date":"1968","value":4.72612546419215,"unit":"","obs_status":"","decimal":1},{"indicator":{"id":"NV.IND.TOTL.KD.ZG","value":"Industry (including construction), value added (annual % growth)"},"country":{"id":"IN","value":"India"},"countryiso3code":"IND","date":"1967","value":3.34143816880345,"unit":"","obs_status":"","decimal":1},{"indicator":{"id":"NV.IND.TOTL.KD.ZG","value":"Industry (including construction), value added (annual % growth)"},"country":{"id":"IN","value":"India"},"countryiso3code":"IND","date":"1966","value":3.56827910757262,"unit":"","obs_status":"","decimal":1},{"indicator":{"id":"NV.IND.TOTL.KD.ZG","value":"Industry (including construction), value added (annual % growth)"},"country":{"id":"IN","value":"India"},"countryiso3code":"IND","date":"1965","value":4.52537682753291,"unit":"","obs_status":"","decimal":1},{"indicator":{"id":"NV.IND.TOTL.KD.ZG","value":"Industry (including construction), value added (annual % growth)"},"country":{"id":"IN","value":"India"},"countryiso3code":"IND","date":"1964","value":6.47926977162463,"unit":"","obs_status":"","decimal":1},{"indicator":{"id":"NV.IND.TOTL.KD.ZG","value":"Industry (including construction), value added (annual % growth)"},"country":{"id":"IN","value":"India"},"countryiso3code":"IND","date":"1963","value":9.44727459195285,"unit":"","obs_status":"","decimal":1},{"indicator":{"id":"NV.IND.TOTL.KD.ZG","value":"Industry (including construction), value added (annual % growth)"},"country":{"id":"IN","value":"India"},"countryiso3code":"IND","date":"1962","value":7.07202792355366,"unit":"","obs_status":"","decimal":1},{"indicator":{"id":"NV.IND.TOTL.KD.ZG","value":"Industry (including construction), value added (annual % growth)"},"country":{"id":"IN","value":"India"},"countryiso3code":"IND","date":"1961","value":6.71267659356647,"unit":"","obs_status":"","decimal":1},{"indicator":{"id":"NV.IND.TOTL.KD.ZG","value":"Industry (including construction), value added (annual % growth)"},"country":{"id":"IN","value":"India"},"countryiso3code":"IND","date":"1960","value":null,"unit":"","obs_status":"","decimal":1}]]